LICENSE
MANIFEST.in
README.md
setup.py
admin_fig/__init__.py
admin_fig/admin.py
admin_fig/apps.py
admin_fig/models.py
admin_fig/tests.py
admin_fig/views.py
admin_fig/migrations/__init__.py
admin_fig/templates/admin/dashboard.html
core/__init__.py
core/asgi.py
core/settings.py
core/urls.py
core/wsgi.py
fig_admin_template.egg-info/PKG-INFO
fig_admin_template.egg-info/SOURCES.txt
fig_admin_template.egg-info/dependency_links.txt
fig_admin_template.egg-info/requires.txt
fig_admin_template.egg-info/top_level.txt