Metadata-Version: 2.1
Name: fig-admin-template
Version: 0.1
Summary: A reusable admin template app for Django projects
Home-page: https://github.com/miladkoohi/fig-admin
Author: Milad Koohi
Author-email: mialdkoohi171@gmail.com
Classifier: Development Status :: 3 - Alpha
Classifier: Framework :: Django
Classifier: Intended Audience :: Developers
Classifier: License :: OSI Approved :: MIT License
Classifier: Programming Language :: Python :: 3
Classifier: Programming Language :: Python :: 3.6
Classifier: Programming Language :: Python :: 3.7
Classifier: Programming Language :: Python :: 3.8
Classifier: Programming Language :: Python :: 3.9
License-File: LICENSE
